artistlib/__init__.py
artistlib/_version.py
artistlib/console.py
artistlib/material.py
artistlib/remote_access.py
artistlib-0.0.6.dist-info/licenses/LICENSE.md
artistlib-0.0.6.dist-info/METADATA
artistlib-0.0.6.dist-info/WHEEL
artistlib-0.0.6.dist-info/top_level.txt
artistlib-0.0.6.dist-info/RECORD
