Metadata-Version: 2.4
Name: artistlib
Version: 0.0.6
Summary: aRTist Python library
Home-page: https://github.com/BAMresearch/aRTist-PythonLib
Author: Carsten Bellon
Author-email: Carsten.Bellon@bam.de
License: Apache 2.0
Classifier: Programming Language :: Python :: 3
Classifier: License :: OSI Approved :: Apache Software License
Classifier: Operating System :: OS Independent
Classifier: Natural Language :: English
Classifier: Topic :: Multimedia :: Graphics :: Graphics Conversion
License-File: LICENSE.md
Dynamic: author
Dynamic: author-email
Dynamic: classifier
Dynamic: description
Dynamic: description-content-type
Dynamic: home-page
Dynamic: license
Dynamic: license-file
Dynamic: summary
